tensor_theorem_prover-0.14.0.dist-info/METADATA
tensor_theorem_prover-0.14.0.dist-info/WHEEL
tensor_theorem_prover-0.14.0.dist-info/license_files/LICENSE
tensor_theorem_prover/normalize/find_unbound_var_names.py
tensor_theorem_prover/normalize/normalize_conjunctions.py
tensor_theorem_prover/normalize/normalize_quantifiers.py
tensor_theorem_prover/normalize/normalize_variables.py
tensor_theorem_prover/normalize/Skolemizer.py
tensor_theorem_prover/normalize/to_cnf.py
tensor_theorem_prover/normalize/to_nnf.py
tensor_theorem_prover/normalize/__init__.py
tensor_theorem_prover/prover/Proof.py
tensor_theorem_prover/prover/ProofStats.py
tensor_theorem_prover/prover/ProofStep.py
tensor_theorem_prover/prover/ResolutionProver.py
tensor_theorem_prover/prover/__init__.py
tensor_theorem_prover/py.typed
tensor_theorem_prover/similarity.py
tensor_theorem_prover/types/Atom.py
tensor_theorem_prover/types/connectives.py
tensor_theorem_prover/types/Constant.py
tensor_theorem_prover/types/Function.py
tensor_theorem_prover/types/Predicate.py
tensor_theorem_prover/types/Term.py
tensor_theorem_prover/types/Variable.py
tensor_theorem_prover/types/__init__.py
tensor_theorem_prover/_rust/__init__.pyi
tensor_theorem_prover/__init__.py
tensor_theorem_prover/_rust.cp38-win_amd64.pyd
tensor_theorem_prover-0.14.0.dist-info/RECORD
