Metadata-Version: 2.1
Name: tensor-theorem-prover
Version: 0.14.0
License-File: LICENSE
Summary: Customizable first-order logic theorem prover supporting approximate vector similarity in unification
Keywords: theorem-proving,logic,first-order,unification,reasoning
Author-email: David Chanin <<chanindav@gmail.com>>
License: MIT
Requires-Python: >=3.8
